haros_plugin_pyflwor/__init__.py
haros_plugin_pyflwor/plugin.py
haros_plugin_pyflwor/plugin.yaml
haros_plugin_pyflwor/pyflwor_monkey_patch.py
haros_plugin_pyflwor-0.2.3.dist-info/LICENSE
haros_plugin_pyflwor-0.2.3.dist-info/METADATA
haros_plugin_pyflwor-0.2.3.dist-info/WHEEL
haros_plugin_pyflwor-0.2.3.dist-info/top_level.txt
haros_plugin_pyflwor-0.2.3.dist-info/RECORD
