Metadata-Version: 2.1
Name: haros-plugin-pyflwor
Version: 0.2.3
Summary: HAROS plugin to query Configurations with Pyflwor.
Home-page: https://github.com/git-afsantos/haros-plugin-pyflwor
Author: André Santos
Author-email: haros.framework@gmail.com
License: MIT
Keywords: ros query architecture model computation-graph
Platform: UNKNOWN
License-File: LICENSE
Requires-Dist: pyflwor-ext (>=1.2)
